aio_connect/__init__.py
aio_connect/exceptions.py
aio_connect/loggers.py
aio_connect/client/__init__.py
aio_connect/client/bot.py
aio_connect/client/context_controller.py
aio_connect/client/session/__init__.py
aio_connect/client/session/aiohttp.py
aio_connect/client/session/base.py
aio_connect/client/session/middlewares/__init__.py
aio_connect/client/session/middlewares/base.py
aio_connect/client/session/middlewares/manager.py
aio_connect/dispatcher/__init__.py
aio_connect/dispatcher/dispatcher.py
aio_connect/dispatcher/router.py
aio_connect/dispatcher/event/__init__.py
aio_connect/dispatcher/event/bases.py
aio_connect/dispatcher/event/connect.py
aio_connect/dispatcher/event/event.py
aio_connect/dispatcher/event/handler.py
aio_connect/dispatcher/middlewares/__init__.py
aio_connect/dispatcher/middlewares/base.py
aio_connect/dispatcher/middlewares/error.py
aio_connect/dispatcher/middlewares/manager.py
aio_connect/dispatcher/middlewares/user_context.py
aio_connect/enums/__init__.py
aio_connect/enums/content_type.py
aio_connect/enums/update_type.py
aio_connect/filters/__init__.py
aio_connect/filters/base.py
aio_connect/filters/command.py
aio_connect/fsm/__init__.py
aio_connect/fsm/context.py
aio_connect/fsm/middleware.py
aio_connect/fsm/state.py
aio_connect/fsm/storage/__init__.py
aio_connect/fsm/storage/base.py
aio_connect/fsm/storage/memory.py
aio_connect/handlers/__init__.py
aio_connect/handlers/base.py
aio_connect/methods/__init__.py
aio_connect/methods/appoint_spec.py
aio_connect/methods/appoint_start.py
aio_connect/methods/base.py
aio_connect/methods/del_all_hook.py
aio_connect/methods/del_hook.py
aio_connect/methods/drop_keyboard.py
aio_connect/methods/drop_treatment.py
aio_connect/methods/get_competences.py
aio_connect/methods/get_lines.py
aio_connect/methods/get_specialist.py
aio_connect/methods/get_specialists.py
aio_connect/methods/get_specialists_available.py
aio_connect/methods/get_subscriber.py
aio_connect/methods/get_subscribers.py
aio_1c_connect-0.0.3.dist-info/LICENSE
aio_1c_connect-0.0.3.dist-info/METADATA
aio_1c_connect-0.0.3.dist-info/WHEEL
aio_1c_connect-0.0.3.dist-info/top_level.txt
aio_1c_connect-0.0.3.dist-info/RECORD
