Metadata-Version: 2.1
Name: aio-1c-connect
Version: 0.0.3
Summary: This is a library for creating bots in the 1C-Connect environment
Home-page: https://github.com/LilKirill00/aio-connect
Author: LilKirill00
Author-email: pc.browsers.1@gmail.com
Project-URL: GitHub, https://github.com/LilKirill00/aio-connect
Keywords: 1C-Connect
Classifier: License :: OSI Approved :: MIT License
Classifier: Development Status :: 5 - Production/Stable
Classifier: Environment :: Console
Classifier: Framework :: AsyncIO
Classifier: Typing :: Typed
Classifier: Intended Audience :: Developers
Classifier: Intended Audience :: System Administrators
Classifier: Programming Language :: Python :: 3.8
Classifier: Programming Language :: Python :: 3.9
Classifier: Programming Language :: Python :: 3.10
Classifier: Programming Language :: Python :: 3.11
Classifier: Programming Language :: Python :: 3.12
Classifier: Programming Language :: Python :: Implementation :: PyPy
Classifier: Topic :: Software Development :: Libraries :: Application Frameworks
Classifier: Topic :: Software Development :: Libraries :: Python Modules
Classifier: Topic :: Communications :: Chat
Requires-Python: >=3.8
License-File: LICENSE
Requires-Dist: magic-filter <1.1,>=1.0.12
Requires-Dist: aiofiles ~=23.2.1
Requires-Dist: aiohttp ~=3.9.0
Requires-Dist: pydantic <2.6,>=2.4.1
